freebie/__init__.py
freebie/util.py
freebie-0.1.3.dist-info/DESCRIPTION.rst
freebie-0.1.3.dist-info/METADATA
freebie-0.1.3.dist-info/RECORD
freebie-0.1.3.dist-info/WHEEL
freebie-0.1.3.dist-info/metadata.json
freebie-0.1.3.dist-info/top_level.txt
freebie-0.1.3.dist-info/zip-safe
