Metadata-Version: 2.0
Name: freebie
Version: 0.1.3
Summary: A free database of news resources for information extraction
Home-page: UNKNOWN
Author: Aleksandar Savkov
Author-email: UNKNOWN
License: GPL3
Platform: UNKNOWN
Classifier: Operating System :: OS Independent
Classifier: Programming Language :: Python
Classifier: Programming Language :: Python :: 3
Classifier: Programming Language :: Python :: 3.2
Classifier: Programming Language :: Python :: 3.3
Classifier: Programming Language :: Python :: 3.4
Classifier: Programming Language :: Python :: 3.5
Classifier: Programming Language :: Python :: 3.6
Classifier: Topic :: Internet :: WWW/HTTP
